robson_package/__init__.py
robson_package/conversor.py
robson_package/robson_package.py
robson_package/trigonometria.py
src/__init__.py
src/robson_package.py
robson_package-0.0.29.dist-info/LICENSE
robson_package-0.0.29.dist-info/METADATA
robson_package-0.0.29.dist-info/WHEEL
robson_package-0.0.29.dist-info/top_level.txt
robson_package-0.0.29.dist-info/RECORD
