Metadata-Version: 2.1
Name: robson-package
Version: 0.0.29
Summary: Meu primeiro pacote em Python
Author: Robson-tech
Author-email: robson.junior@ufpi.edu.br
License: MIT
License-File: LICENSE
